equoai_node/__init__.py
equoai_node/main.py
equoai_node-1.0.0.dist-info/METADATA
equoai_node-1.0.0.dist-info/WHEEL
equoai_node-1.0.0.dist-info/top_level.txt
equoai_node-1.0.0.dist-info/RECORD
